cosmos/__init__.py
cosmos/config.py
cosmos/constants.py
cosmos/converter.py
cosmos/exceptions.py
cosmos/log.py
cosmos/airflow/__init__.py
cosmos/airflow/dag.py
cosmos/airflow/graph.py
cosmos/airflow/task_group.py
cosmos/core/__init__.py
cosmos/core/airflow.py
cosmos/core/graph/__init__.py
cosmos/core/graph/entities.py
cosmos/dbt/__init__.py
cosmos/dbt/executable.py
cosmos/dbt/graph.py
cosmos/dbt/project.py
cosmos/dbt/selector.py
cosmos/dbt/parser/__init__.py
cosmos/dbt/parser/output.py
cosmos/dbt/parser/project.py
cosmos/hooks/__init__.py
cosmos/hooks/subprocess.py
cosmos/operators/__init__.py
cosmos/operators/azure_container_instance.py
cosmos/operators/base.py
cosmos/operators/docker.py
cosmos/operators/kubernetes.py
cosmos/operators/lazy_load.py
cosmos/operators/local.py
cosmos/operators/virtualenv.py
cosmos/plugin/__init__.py
cosmos/plugin/static/iframeResizer.contentWindow.min.js
cosmos/plugin/static/iframeResizer.min.js
cosmos/plugin/templates/dbt_docs.html
cosmos/plugin/templates/dbt_docs_not_set_up.html
cosmos/profiles/__init__.py
cosmos/profiles/base.py
cosmos/profiles/athena/__init__.py
cosmos/profiles/athena/access_key.py
cosmos/profiles/bigquery/__init__.py
cosmos/profiles/bigquery/oauth.py
cosmos/profiles/bigquery/service_account_file.py
cosmos/profiles/bigquery/service_account_keyfile_dict.py
cosmos/profiles/databricks/__init__.py
cosmos/profiles/databricks/token.py
cosmos/profiles/exasol/__init__.py
cosmos/profiles/exasol/user_pass.py
cosmos/profiles/postgres/__init__.py
cosmos/profiles/postgres/user_pass.py
cosmos/profiles/redshift/__init__.py
cosmos/profiles/redshift/user_pass.py
cosmos/profiles/snowflake/__init__.py
cosmos/profiles/snowflake/user_encrypted_privatekey_env_variable.py
cosmos/profiles/snowflake/user_encrypted_privatekey_file.py
cosmos/profiles/snowflake/user_pass.py
cosmos/profiles/snowflake/user_privatekey.py
cosmos/profiles/spark/__init__.py
cosmos/profiles/spark/thrift.py
cosmos/profiles/trino/__init__.py
astronomer_cosmossss-1.4.0a1.dist-info/METADATA
astronomer_cosmossss-1.4.0a1.dist-info/WHEEL
astronomer_cosmossss-1.4.0a1.dist-info/entry_points.txt
astronomer_cosmossss-1.4.0a1.dist-info/licenses/LICENSE
astronomer_cosmossss-1.4.0a1.dist-info/RECORD
