Metadata-Version: 2.3
Name: astronomer-cosmossss
Version: 1.4.0a1
Summary: Orchestrate your dbt projects in Airflow
Project-URL: Homepage, https://github.com/astronomer/astronomer-cosmos
Project-URL: Documentation, https://astronomer.github.io/astronomer-cosmos
Project-URL: Source code, https://github.com/astronomer/astronomer-cosmos
Author-email: Astronomer <humans@astronomer.io>
License-Expression: Apache-2.0
License-File: LICENSE
Keywords: airflow,apache-airflow,astronomer,dags,dbt
Classifier: Development Status :: 3 - Alpha
Classifier: Environment :: Web Environment
Classifier: Framework :: Apache Airflow
Classifier: Framework :: Apache Airflow :: Provider
Classifier: Intended Audience :: Developers
Classifier: License :: OSI Approved :: Apache Software License
Classifier: Operating System :: OS Independent
Classifier: Programming Language :: Python
Classifier: Programming Language :: Python :: 3
Classifier: Programming Language :: Python :: 3.8
Classifier: Programming Language :: Python :: 3.9
Classifier: Programming Language :: Python :: 3.10
Classifier: Programming Language :: Python :: 3.11
Requires-Python: >=3.8
Requires-Dist: aenum
Requires-Dist: apache-airflow>=2.3.0
Requires-Dist: attrs
Requires-Dist: importlib-metadata; python_version < '3.8'
Requires-Dist: jinja2>=3.0.0
Requires-Dist: typing-extensions; python_version < '3.8'
Requires-Dist: virtualenv
Provides-Extra: all
Requires-Dist: astronomer-cosmos[dbt-all]; extra == 'all'
Requires-Dist: astronomer-cosmos[openlineage]; extra == 'all'
Provides-Extra: azure-container-instance
Requires-Dist: apache-airflow-providers-microsoft-azure>=8.4.0; extra == 'azure-container-instance'
Provides-Extra: dbt-all
Requires-Dist: dbt-athena; extra == 'dbt-all'
Requires-Dist: dbt-bigquery; extra == 'dbt-all'
Requires-Dist: dbt-databricks; extra == 'dbt-all'
Requires-Dist: dbt-exasol; extra == 'dbt-all'
Requires-Dist: dbt-postgres; extra == 'dbt-all'
Requires-Dist: dbt-redshift; extra == 'dbt-all'
Requires-Dist: dbt-snowflake; extra == 'dbt-all'
Requires-Dist: dbt-spark; extra == 'dbt-all'
Requires-Dist: dbt-vertica; extra == 'dbt-all'
Provides-Extra: dbt-athena
Requires-Dist: apache-airflow-providers-amazon>=8.0.0; extra == 'dbt-athena'
Requires-Dist: dbt-athena-community; extra == 'dbt-athena'
Provides-Extra: dbt-bigquery
Requires-Dist: dbt-bigquery; extra == 'dbt-bigquery'
Provides-Extra: dbt-databricks
Requires-Dist: dbt-databricks; extra == 'dbt-databricks'
Provides-Extra: dbt-exasol
Requires-Dist: dbt-exasol; extra == 'dbt-exasol'
Provides-Extra: dbt-postgres
Requires-Dist: dbt-postgres; extra == 'dbt-postgres'
Provides-Extra: dbt-redshift
Requires-Dist: dbt-redshift; extra == 'dbt-redshift'
Provides-Extra: dbt-snowflake
Requires-Dist: dbt-snowflake; extra == 'dbt-snowflake'
Provides-Extra: dbt-spark
Requires-Dist: dbt-spark; extra == 'dbt-spark'
Provides-Extra: dbt-vertica
Requires-Dist: dbt-vertica<=1.5.4; extra == 'dbt-vertica'
Provides-Extra: docker
Requires-Dist: apache-airflow-providers-docker>=3.5.0; extra == 'docker'
Provides-Extra: docs
Requires-Dist: apache-airflow-providers-cncf-kubernetes>=5.1.1; extra == 'docs'
Requires-Dist: pydata-sphinx-theme; extra == 'docs'
Requires-Dist: sphinx; extra == 'docs'
Requires-Dist: sphinx-autoapi; extra == 'docs'
Requires-Dist: sphinx-autobuild; extra == 'docs'
Provides-Extra: kubernetes
Requires-Dist: apache-airflow-providers-cncf-kubernetes>=5.1.1; extra == 'kubernetes'
Provides-Extra: openlineage
Requires-Dist: openlineage-airflow; extra == 'openlineage'
Requires-Dist: openlineage-integration-common; extra == 'openlineage'
Provides-Extra: pydantic
Requires-Dist: pydantic>=1.10.0; extra == 'pydantic'
Provides-Extra: tests
Requires-Dist: mypy; extra == 'tests'
Requires-Dist: packaging; extra == 'tests'
Requires-Dist: pytest-cov; extra == 'tests'
Requires-Dist: pytest-describe; extra == 'tests'
Requires-Dist: pytest-dotenv; extra == 'tests'
Requires-Dist: pytest-split; extra == 'tests'
Requires-Dist: pytest>=6.0; extra == 'tests'
Requires-Dist: requests-mock; extra == 'tests'
Requires-Dist: sqlalchemy-stubs; extra == 'tests'
Requires-Dist: types-requests; extra == 'tests'
